dxlmispclient/__init__.py
dxlmispclient/_version.py
dxlmispclient/client.py
dxlmispclient/_config/__init__.py
dxlmispclient/_config/sample/__init__.py
dxlmispclient/_config/sample/dxlclient.config
dxlmispclient-0.1.0.dist-info/METADATA
dxlmispclient-0.1.0.dist-info/RECORD
dxlmispclient-0.1.0.dist-info/WHEEL
dxlmispclient-0.1.0.dist-info/top_level.txt
